setup.py
rendermarkdown/__init__.py
rendermarkdown/cli.py
rendermarkdown.egg-info/PKG-INFO
rendermarkdown.egg-info/SOURCES.txt
rendermarkdown.egg-info/dependency_links.txt
rendermarkdown.egg-info/entry_points.txt
rendermarkdown.egg-info/requires.txt
rendermarkdown.egg-info/top_level.txt