Metadata-Version: 1.0
Name: rendermarkdown
Version: 0.0.2
Summary: A simple CLI to preview markdown files (i.e "README.md") files using GitHubs API
Home-page: https://github.com/whalerock/rendermarkdown
Author: Matt Chung
Author-email: mchung@whalerockindustries.com
License: UNKNOWN
Platform: UNKNOWN
